{
  "project_info": {
    "project_number": "529415271397",
    "project_id": "fruit-hub-51083",
    "storage_bucket": "fruit-hub-51083.appspot.com"
  },
  "client": [
    {
      "client_info": {
        "mobilesdk_app_id": "1:529415271397:android:5064bbf4b79e8de2fc750c",
        "android_client_info": {
          "package_name": "com.example.fruitHub"
        }
      },
      "oauth_client": [],
      "api_key": [
        {
          "current_key": "AIzaSyCr4XaNVHoK5rmUZ3qxXDLEWytSShULuJU"
        }
      ],
      "services": {
        "appinvite_service": {
          "other_platform_oauth_client": []
        }
      }
    }
  ],
  "configuration_version": "1"
}